<?xml version="1.0" encoding="utf-8"?>
<CHI_TIEU_DU_LIEU_TOM_TAT_HO_SO_BENH_AN>
  <MA_LK></MA_LK>
  <MA_LOAI_KCB></MA_LOAI_KCB>
  <HO_TEN_CHA></HO_TEN_CHA>
  <HO_TEN_ME></HO_TEN_ME>
  <NGUOI_GIAM_HO></NGUOI_GIAM_HO>
  <DON_VI></DON_VI>
  <NGAY_VAO></NGAY_VAO>
  <NGAY_RA></NGAY_RA>
  <CHAN_DOAN_VAO></CHAN_DOAN_VAO>
  <CHAN_DOAN_RV></CHAN_DOAN_RV>
  <QT_BENHLY></QT_BENHLY>
  <TOMTAT_KQ></TOMTAT_KQ>
  <PP_DIEUTRI></PP_DIEUTRI>
  <NGAY_SINHCON></NGAY_SINHCON>
  <NGAY_CONCHET></NGAY_CONCHET>
  <SO_CONCHET></SO_CONCHET>
  <KET_QUA_DTRI></KET_QUA_DTRI>
  <GHI_CHU></GHI_CHU>
  <MA_TTDV></MA_TTDV>
  <NGAY_CT></NGAY_CT>
  <MA_THE_TAM></MA_THE_TAM>
  <DU_PHONG></DU_PHONG>
</CHI_TIEU_DU_LIEU_TOM_TAT_HO_SO_BENH_AN>
